modaic/__init__.py
modaic/auto.py
modaic/constants.py
modaic/datasets.py
modaic/exceptions.py
modaic/hub.py
modaic/module_utils.py
modaic/observability.py
modaic/precompiled.py
modaic/serializers.py
modaic/utils.py
modaic/programs/__init__.py
modaic/programs/predict.py
modaic/programs/rag_program.py
modaic/programs/registry.py
modaic-0.10.0.dist-info/METADATA
modaic-0.10.0.dist-info/WHEEL
modaic-0.10.0.dist-info/licenses/LICENSE
modaic-0.10.0.dist-info/RECORD
