Metadata-Version: 2.4
Name: modaic
Version: 0.10.0
Summary: Modular Agent Infrastructure Collection, a python framework for managing and sharing DSPy agents
Project-URL: Homepage, https://github.com/modaic-ai/modaic
Project-URL: Modaic, https://www.modaic.dev
Project-URL: Docs, https://docs.modaic.dev
Author-email: Tyrin <tytodd@mit.edu>, Farouk <farouk@modaic.dev>
License: MIT License
License-File: LICENSE
Requires-Python: >=3.10
Requires-Dist: dspy>=2.6.27
Requires-Dist: gitpython>=3.1.45
Requires-Dist: opik==1.8.42
Requires-Dist: platformdirs>=4.3.8
Requires-Dist: tomlkit>=0.13.3
